{"active_state_hash":"29412586c460b63d","actor":"tong0202","completed_steps":1,"created_at":"2026-07-10T19:55:10.709932+00:00","end_seq":51,"event_name":"schedule","github_run_attempt":"1","github_run_id":"29119615141","hold_state_hash":"e7e21bc559b18612","last_run_hash":"603141a2d6b6f0cd","ok":true,"run_id":"nc14-remote-29119615141-attempt-1","schema_version":"QMX-NC-14-LAST-RUN-0.1","stage":"NC-14-remote-transition-last-run","start_seq":51,"steps":1,"truth_boundary":"NC-14 proves controlled remote platform transition writing, not CPU-free network-native computation.","writes":[{"ok":true,"op":"remote_invert","payload_hash":"65738107e1cabec6","prev_state_hash":"f133ed604e4c7ce4","seq":51,"state_hash":"29412586c460b63d","write":{"attempt_count":1,"ok":true,"path":"states/nc-13-transition/active.json","sha":"497edc0c12e411a3c94c1b3f5d61d4c73fb1f9a7"}}]}