{
  "stage": "E7-last-run",
  "schema_version": "QMX-E7-LAST-RUN-0.1",
  "created_at": "2026-07-16T22:17:27.210069+00:00",
  "run_id": "nsl-e7-schedule-29539038355-attempt-1",
  "owner": {
    "mode": "external",
    "workflow": "E7 Controlled Vitals Self Maintenance",
    "run_id": "29539038355",
    "run_attempt": "1",
    "event_name": "schedule",
    "actor": "tong0202",
    "repository": "tong0202/qimingxing-test2-network-state-20260626-034447",
    "sha": "b7fd085570c6a04b66db441ee80433cbb83591e3",
    "local": false
  },
  "ok": true,
  "evidence_level": "E7-controlled-low-risk-self-maintenance-v0",
  "generation": 474,
  "maintenance_ok": true,
  "executed_count": 4,
  "blocked_count": 4,
  "state_hash": "b4ded01dc9a8800a",
  "plan_hash": "65c0e4e8b698a644",
  "actions_hash": "874c73f7183bdf57",
  "truth_boundary": "E7 is controlled low-risk self-maintenance executed by local or GitHub Actions CPU. It records health and no-op repair receipts only; it does not modify core code, workflows, permissions, or prove CPU-free network self-execution.",
  "last_run_hash": "1c0fa8bc10ce6df5"
}
