{
  "stage": "E7-last-run",
  "schema_version": "QMX-E7-LAST-RUN-0.1",
  "created_at": "2026-07-04T12:18:50.418370+00:00",
  "run_id": "nsl-e7-schedule-28705975634-attempt-1",
  "owner": {
    "mode": "external",
    "workflow": "E7.1 External Wake Timer",
    "run_id": "28705975634",
    "run_attempt": "1",
    "event_name": "schedule",
    "actor": "tong0202",
    "repository": "tong0202/qimingxing-test2-network-state-20260626-034447",
    "sha": "3406cb12156ce7950dc94b7bde54985b26c8d4e3",
    "local": false
  },
  "ok": true,
  "evidence_level": "E7-controlled-low-risk-self-maintenance-v0",
  "generation": 145,
  "maintenance_ok": true,
  "executed_count": 4,
  "blocked_count": 4,
  "state_hash": "acff6fd38462eec8",
  "plan_hash": "ed6577950a0e0898",
  "actions_hash": "93803ccb3f67b771",
  "truth_boundary": "E7 is controlled low-risk self-maintenance executed by local or GitHub Actions CPU. It records health and no-op repair receipts only; it does not modify core code, workflows, permissions, or prove CPU-free network self-execution.",
  "last_run_hash": "7f11f3b9de2650fb"
}
