{
  "stage": "E8.4-ledger-report",
  "schema_version": "QMX-E8.4-REPORT-0.1",
  "created_at": "2026-07-17T18:54:41.164748+00:00",
  "run_id": "nsl-e8-2-schedule-29605450214-attempt-1",
  "ok": true,
  "entry_count": 455,
  "ready_count": 424,
  "covered_workflows": [
    "E7 Controlled Vitals Self Maintenance",
    "E7.1 External Wake Timer",
    "E7.3a HTTP Bridge Entry",
    "E8.2 Post Wake Self Maintenance"
  ],
  "covered_events": [
    "repository_dispatch",
    "schedule",
    "workflow_dispatch"
  ],
  "latest_entry_run_id": "nsl-e8-2-schedule-29605450214-attempt-1",
  "ledger_hash": "19b94cfcb4f41e8c",
  "conclusion": "E8.4 records post-wake self-check receipts into a unified deduplicated ledger.",
  "truth_boundary": "E8.4 is a mutable GitHub state ledger rebuilt from immutable per-run snapshots and the current result. It improves auditability but is not a tamper-proof database and does not prove CPU-free wakefulness.",
  "report_hash": "c407d9192f99febf"
}
