{
  "stage": "E8.5-recent-post-wake",
  "schema_version": "QMX-E8.5-RECENT-0.1",
  "created_at": "2026-07-10T22:48:01.062425+00:00",
  "run_id": "nsl-e8-5-schedule-29128565924-attempt-1",
  "owner": {
    "mode": "external",
    "workflow": "E7.1 External Wake Timer",
    "run_id": "29128565924",
    "run_attempt": "1",
    "event_name": "schedule",
    "actor": "tong0202",
    "repository": "tong0202/qimingxing-test2-network-state-20260626-034447",
    "sha": "9bdbe9c0af4c98a2281c6cc74e2d7aa33beaf62b",
    "local": false
  },
  "summary_hash": "e434c6b836299d2f",
  "recent_limit": 8,
  "recent_count": 8,
  "recent_ready_count": 8,
  "status_level": "healthy_with_known_gaps",
  "entries": [
    {
      "run_id": "nsl-e8-2-schedule-29115907869-attempt-1",
      "created_at": "2026-07-10T18:49:52.365361+00:00",
      "ok": true,
      "post_wake_ready": true,
      "workflow": "E7 Controlled Vitals Self Maintenance",
      "event_name": "schedule",
      "owner_run_id": "29115907869",
      "state_hash": "a3d0a6d303ed3139",
      "snapshot_hash": "368076907e13a9ef",
      "entry_hash": "d62a13440fd14657",
      "external_clock_pending": true,
      "e7_latest_event_name": "schedule"
    },
    {
      "run_id": "nsl-e8-2-schedule-29116889210-attempt-1",
      "created_at": "2026-07-10T19:07:36.457537+00:00",
      "ok": true,
      "post_wake_ready": true,
      "workflow": "E7.1 External Wake Timer",
      "event_name": "schedule",
      "owner_run_id": "29116889210",
      "state_hash": "38d27dec003e2ef8",
      "snapshot_hash": "96d1ad71b304d2a6",
      "entry_hash": "569a47ce5363d653",
      "external_clock_pending": true,
      "e7_latest_event_name": "schedule"
    },
    {
      "run_id": "nsl-e8-2-schedule-29120335023-attempt-1",
      "created_at": "2026-07-10T20:08:08.421263+00:00",
      "ok": true,
      "post_wake_ready": true,
      "workflow": "E7 Controlled Vitals Self Maintenance",
      "event_name": "schedule",
      "owner_run_id": "29120335023",
      "state_hash": "dc6f48a148dba600",
      "snapshot_hash": "2a1de5560adfca12",
      "entry_hash": "cc1797adf9155903",
      "external_clock_pending": true,
      "e7_latest_event_name": "schedule"
    },
    {
      "run_id": "nsl-e8-2-schedule-29122234024-attempt-1",
      "created_at": "2026-07-10T20:41:26.787343+00:00",
      "ok": true,
      "post_wake_ready": true,
      "workflow": "E7.1 External Wake Timer",
      "event_name": "schedule",
      "owner_run_id": "29122234024",
      "state_hash": "a5470f74c51a9fa4",
      "snapshot_hash": "dd8676b2a5cecea6",
      "entry_hash": "b051a1c55460d280",
      "external_clock_pending": true,
      "e7_latest_event_name": "schedule"
    },
    {
      "run_id": "nsl-e8-2-schedule-29124234989-attempt-1",
      "created_at": "2026-07-10T21:18:24.332732+00:00",
      "ok": true,
      "post_wake_ready": true,
      "workflow": "E7 Controlled Vitals Self Maintenance",
      "event_name": "schedule",
      "owner_run_id": "29124234989",
      "state_hash": "1c4da4815caef6ed",
      "snapshot_hash": "b212246641717837",
      "entry_hash": "092593a18b3d48c0",
      "external_clock_pending": true,
      "e7_latest_event_name": "schedule"
    },
    {
      "run_id": "nsl-e8-2-schedule-29125556181-attempt-1",
      "created_at": "2026-07-10T21:43:24.501609+00:00",
      "ok": true,
      "post_wake_ready": true,
      "workflow": "E7.1 External Wake Timer",
      "event_name": "schedule",
      "owner_run_id": "29125556181",
      "state_hash": "fc361b67ef8e6a9d",
      "snapshot_hash": "b8afbc366a55f488",
      "entry_hash": "43f09c2d9ed272c4",
      "external_clock_pending": true,
      "e7_latest_event_name": "schedule"
    },
    {
      "run_id": "nsl-e8-2-schedule-29127386077-attempt-1",
      "created_at": "2026-07-10T22:19:58.334735+00:00",
      "ok": true,
      "post_wake_ready": true,
      "workflow": "E7 Controlled Vitals Self Maintenance",
      "event_name": "schedule",
      "owner_run_id": "29127386077",
      "state_hash": "453bf48c1f71ee48",
      "snapshot_hash": "65533c0d108fbdc0",
      "entry_hash": "de6a8410358cec53",
      "external_clock_pending": true,
      "e7_latest_event_name": "schedule"
    },
    {
      "run_id": "nsl-e8-2-schedule-29128565924-attempt-1",
      "created_at": "2026-07-10T22:45:13.441803+00:00",
      "ok": true,
      "post_wake_ready": true,
      "workflow": "E7.1 External Wake Timer",
      "event_name": "schedule",
      "owner_run_id": "29128565924",
      "state_hash": "fcff4b4d61072cff",
      "snapshot_hash": "82bb9276b0d5bc70",
      "entry_hash": "90f025bd45b36e31",
      "external_clock_pending": true,
      "e7_latest_event_name": "schedule"
    }
  ],
  "recent_hash": "7649b0760bdf63b4"
}
