{
  "ok": true,
  "stage": "N7-external-breakpoint-recovery-and-anti-reentry",
  "started_at": "2026-06-30T04:49:54.307182+00:00",
  "finished_at": "2026-06-30T04:50:00.459759+00:00",
  "previous_generation": 64,
  "next_generation": 65,
  "decision": {
    "phase": "active",
    "event": "fast_release",
    "reason": "previous branch shadow released quickly"
  },
  "stale_lock_clear": null,
  "lock": {
    "acquire": {
      "ok": true,
      "status": 200,
      "content_sha": "073b0f45ae45673cfed13386b226f3d83ac10ed1"
    },
    "state_written_checkpoint": {
      "ok": true,
      "status": 200,
      "error": ""
    },
    "final": {
      "checkpoint": "completed",
      "locked": false,
      "ok": true,
      "status": 200,
      "error": ""
    }
  },
  "write": {
    "ok": true,
    "status": 200,
    "commit_hash": "ae4a87a6ce1fefe1b9789c98cc50e84a85e9af23",
    "content_sha": "7f8e4ffc98de255cdb5eef18cf6ac7522d60cf42"
  },
  "commit_verify": {
    "ok": true,
    "generations": [
      65,
      65,
      65
    ],
    "x_cache": [
      "MISS",
      "HIT",
      "HIT"
    ],
    "samples": [
      {
        "ok": true,
        "status": 200,
        "elapsed_ms": 68.57,
        "generation": 65,
        "phase": "active",
        "state_signature": "58b377b1094b3add",
        "body_sha16": "cbb8b36fb6a8a285",
        "canonical_sha16": "3d7912504fa1e532",
        "payload": {
          "stage": "N7-externalized-ghost-state-machine-with-lock",
          "created_at": "2026-06-30T04:49:55.364078+00:00",
          "generation": 65,
          "cycle_index": 57,
          "phase": "active",
          "event": "fast_release",
          "decision_reason": "previous branch shadow released quickly",
          "previous": {
            "generation": 64,
            "phase": "active",
            "state_signature": "e06dd0c44dbd026f"
          },
          "release_memory": {
            "count": 63,
            "latest_seconds": 0.34,
            "mean_seconds": 143.755,
            "pending_current_release": true
          },
          "executor": {
            "layer": "github_actions",
            "workflow": "N6 External Ghost Runner",
            "run_id": "28421070324",
            "run_attempt": "1",
            "actor": "tong0202",
            "repository": "tong0202/qimingxing-test2-network-state-20260626-034447",
            "server_url": "https://github.com"
          },
          "network_role": {
            "N7": "GitHub Actions reads, claims a state lock, decides, writes back, waits for Raw release, finalizes, and prevents duplicate external mutation"
          },
          "state_signature": "58b377b1094b3add",
          "truth_boundary": "N7 is externalized execution on GitHub Actions with checkpoint recovery and anti-reentry. It is still physical cloud CPU, not network-only computation."
        },
        "headers": {
          "cache-control": "max-age=300",
          "etag": "\"a5fab2c7873cc9b430b604d0b40a31839391e428ef83e5ef71aee60b249f7216\"",
          "x-cache": "MISS",
          "x-served-by": "cache-iad-kcgs7200133-IAD",
          "via": "1.1 varnish",
          "expires": "Tue, 30 Jun 2026 04:54:56 GMT"
        },
        "error": "",
        "index": 1,
        "sampled_at": "2026-06-30T04:49:56.902919+00:00"
      },
      {
        "ok": true,
        "status": 200,
        "elapsed_ms": 11.03,
        "generation": 65,
        "phase": "active",
        "state_signature": "58b377b1094b3add",
        "body_sha16": "cbb8b36fb6a8a285",
        "canonical_sha16": "3d7912504fa1e532",
        "payload": {
          "stage": "N7-externalized-ghost-state-machine-with-lock",
          "created_at": "2026-06-30T04:49:55.364078+00:00",
          "generation": 65,
          "cycle_index": 57,
          "phase": "active",
          "event": "fast_release",
          "decision_reason": "previous branch shadow released quickly",
          "previous": {
            "generation": 64,
            "phase": "active",
            "state_signature": "e06dd0c44dbd026f"
          },
          "release_memory": {
            "count": 63,
            "latest_seconds": 0.34,
            "mean_seconds": 143.755,
            "pending_current_release": true
          },
          "executor": {
            "layer": "github_actions",
            "workflow": "N6 External Ghost Runner",
            "run_id": "28421070324",
            "run_attempt": "1",
            "actor": "tong0202",
            "repository": "tong0202/qimingxing-test2-network-state-20260626-034447",
            "server_url": "https://github.com"
          },
          "network_role": {
            "N7": "GitHub Actions reads, claims a state lock, decides, writes back, waits for Raw release, finalizes, and prevents duplicate external mutation"
          },
          "state_signature": "58b377b1094b3add",
          "truth_boundary": "N7 is externalized execution on GitHub Actions with checkpoint recovery and anti-reentry. It is still physical cloud CPU, not network-only computation."
        },
        "headers": {
          "cache-control": "max-age=300",
          "etag": "\"a5fab2c7873cc9b430b604d0b40a31839391e428ef83e5ef71aee60b249f7216\"",
          "x-cache": "HIT",
          "x-served-by": "cache-iad-kiad7000148-IAD",
          "via": "1.1 varnish",
          "expires": "Tue, 30 Jun 2026 04:54:57 GMT"
        },
        "error": "",
        "index": 2,
        "sampled_at": "2026-06-30T04:49:57.914286+00:00"
      },
      {
        "ok": true,
        "status": 200,
        "elapsed_ms": 11.15,
        "generation": 65,
        "phase": "active",
        "state_signature": "58b377b1094b3add",
        "body_sha16": "cbb8b36fb6a8a285",
        "canonical_sha16": "3d7912504fa1e532",
        "payload": {
          "stage": "N7-externalized-ghost-state-machine-with-lock",
          "created_at": "2026-06-30T04:49:55.364078+00:00",
          "generation": 65,
          "cycle_index": 57,
          "phase": "active",
          "event": "fast_release",
          "decision_reason": "previous branch shadow released quickly",
          "previous": {
            "generation": 64,
            "phase": "active",
            "state_signature": "e06dd0c44dbd026f"
          },
          "release_memory": {
            "count": 63,
            "latest_seconds": 0.34,
            "mean_seconds": 143.755,
            "pending_current_release": true
          },
          "executor": {
            "layer": "github_actions",
            "workflow": "N6 External Ghost Runner",
            "run_id": "28421070324",
            "run_attempt": "1",
            "actor": "tong0202",
            "repository": "tong0202/qimingxing-test2-network-state-20260626-034447",
            "server_url": "https://github.com"
          },
          "network_role": {
            "N7": "GitHub Actions reads, claims a state lock, decides, writes back, waits for Raw release, finalizes, and prevents duplicate external mutation"
          },
          "state_signature": "58b377b1094b3add",
          "truth_boundary": "N7 is externalized execution on GitHub Actions with checkpoint recovery and anti-reentry. It is still physical cloud CPU, not network-only computation."
        },
        "headers": {
          "cache-control": "max-age=300",
          "etag": "\"a5fab2c7873cc9b430b604d0b40a31839391e428ef83e5ef71aee60b249f7216\"",
          "x-cache": "HIT",
          "x-served-by": "cache-iad-kiad7000117-IAD",
          "via": "1.1 varnish",
          "expires": "Tue, 30 Jun 2026 04:54:58 GMT"
        },
        "error": "",
        "index": 3,
        "sampled_at": "2026-06-30T04:49:58.925770+00:00"
      }
    ]
  },
  "branch_release": {
    "released": true,
    "release_after_seconds": 0.06,
    "branch_generations": [
      65
    ],
    "branch_signatures": [
      "58b377b1094b3add"
    ],
    "branch_x_cache": [
      "MISS"
    ],
    "samples": [
      {
        "index": 1,
        "sampled_at": "2026-06-30T04:49:58.990133+00:00",
        "elapsed_since_write": 0.06,
        "branch": {
          "ok": true,
          "status": 200,
          "elapsed_ms": 64.2,
          "generation": 65,
          "phase": "active",
          "state_signature": "58b377b1094b3add",
          "body_sha16": "cbb8b36fb6a8a285",
          "canonical_sha16": "3d7912504fa1e532",
          "payload": {
            "stage": "N7-externalized-ghost-state-machine-with-lock",
            "created_at": "2026-06-30T04:49:55.364078+00:00",
            "generation": 65,
            "cycle_index": 57,
            "phase": "active",
            "event": "fast_release",
            "decision_reason": "previous branch shadow released quickly",
            "previous": {
              "generation": 64,
              "phase": "active",
              "state_signature": "e06dd0c44dbd026f"
            },
            "release_memory": {
              "count": 63,
              "latest_seconds": 0.34,
              "mean_seconds": 143.755,
              "pending_current_release": true
            },
            "executor": {
              "layer": "github_actions",
              "workflow": "N6 External Ghost Runner",
              "run_id": "28421070324",
              "run_attempt": "1",
              "actor": "tong0202",
              "repository": "tong0202/qimingxing-test2-network-state-20260626-034447",
              "server_url": "https://github.com"
            },
            "network_role": {
              "N7": "GitHub Actions reads, claims a state lock, decides, writes back, waits for Raw release, finalizes, and prevents duplicate external mutation"
            },
            "state_signature": "58b377b1094b3add",
            "truth_boundary": "N7 is externalized execution on GitHub Actions with checkpoint recovery and anti-reentry. It is still physical cloud CPU, not network-only computation."
          },
          "headers": {
            "cache-control": "max-age=300",
            "etag": "\"a5fab2c7873cc9b430b604d0b40a31839391e428ef83e5ef71aee60b249f7216\"",
            "x-cache": "MISS",
            "x-served-by": "cache-iad-kiad7000158-IAD",
            "via": "1.1 varnish",
            "expires": "Tue, 30 Jun 2026 04:54:58 GMT"
          },
          "error": ""
        },
        "released": true
      }
    ]
  },
  "finalize": {
    "ok": true,
    "status": 200,
    "error": ""
  },
  "final_state": {
    "stage": "N7-externalized-ghost-state-machine-with-lock",
    "created_at": "2026-06-30T04:49:55.364078+00:00",
    "generation": 65,
    "cycle_index": 57,
    "phase": "active",
    "event": "fast_release",
    "decision_reason": "previous branch shadow released quickly",
    "previous": {
      "generation": 64,
      "phase": "active",
      "state_signature": "e06dd0c44dbd026f"
    },
    "release_memory": {
      "count": 64,
      "latest_seconds": 0.06,
      "mean_seconds": 141.51,
      "pending_current_release": false
    },
    "executor": {
      "layer": "github_actions",
      "workflow": "N6 External Ghost Runner",
      "run_id": "28421070324",
      "run_attempt": "1",
      "actor": "tong0202",
      "repository": "tong0202/qimingxing-test2-network-state-20260626-034447",
      "server_url": "https://github.com"
    },
    "network_role": {
      "N7": "GitHub Actions reads, claims a state lock, decides, writes back, waits for Raw release, finalizes, and prevents duplicate external mutation"
    },
    "state_signature": "65e7b9bf9b38c23a",
    "truth_boundary": "N7 is externalized execution on GitHub Actions with checkpoint recovery and anti-reentry. It is still physical cloud CPU, not network-only computation.",
    "self_release": {
      "release_after_seconds": 0.06,
      "observed_at": "2026-06-30T04:49:58.990738+00:00"
    }
  },
  "truth_boundary": "N7 proves external checkpointing and anti-reentry on GitHub Actions. It still uses GitHub cloud CPU and does not prove hardware-free network computation."
}
