{
  "ok": true,
  "stage": "N7-external-breakpoint-recovery-and-anti-reentry",
  "started_at": "2026-07-17T20:33:40.724734+00:00",
  "finished_at": "2026-07-17T20:33:47.878804+00:00",
  "previous_generation": 257,
  "next_generation": 258,
  "decision": {
    "phase": "active",
    "event": "fast_release",
    "reason": "previous branch shadow released quickly"
  },
  "stale_lock_clear": null,
  "lock": {
    "acquire": {
      "ok": true,
      "status": 200,
      "content_sha": "99968462e95f43cef40014daa786e41b734a4086"
    },
    "state_written_checkpoint": {
      "ok": true,
      "status": 200,
      "error": ""
    },
    "final": {
      "checkpoint": "completed",
      "locked": false,
      "ok": true,
      "status": 200,
      "error": ""
    }
  },
  "write": {
    "ok": true,
    "status": 200,
    "commit_hash": "d8249e26b803b3918ed07ff0469cd370950ec4b6",
    "content_sha": "eeb2222b5ca87f023fe7704f3902aeb9fb77da3f"
  },
  "commit_verify": {
    "ok": true,
    "generations": [
      258,
      258,
      258
    ],
    "x_cache": [
      "MISS",
      "HIT",
      "HIT"
    ],
    "samples": [
      {
        "ok": true,
        "status": 200,
        "elapsed_ms": 136.81,
        "generation": 258,
        "phase": "active",
        "state_signature": "d837f39dae9c875a",
        "body_sha16": "9826a30dac221358",
        "canonical_sha16": "5bb4feed1dedc993",
        "payload": {
          "stage": "N7-externalized-ghost-state-machine-with-lock",
          "created_at": "2026-07-17T20:33:42.092475+00:00",
          "generation": 258,
          "cycle_index": 250,
          "phase": "active",
          "event": "fast_release",
          "decision_reason": "previous branch shadow released quickly",
          "previous": {
            "generation": 257,
            "phase": "active",
            "state_signature": "ed8bdb91ba1e3128"
          },
          "release_memory": {
            "count": 256,
            "latest_seconds": 0.08,
            "mean_seconds": 332.276,
            "pending_current_release": true
          },
          "executor": {
            "layer": "github_actions",
            "workflow": "N6 External Ghost Runner",
            "run_id": "29611645401",
            "run_attempt": "1",
            "actor": "tong0202",
            "repository": "tong0202/qimingxing-test2-network-state-20260626-034447",
            "server_url": "https://github.com"
          },
          "network_role": {
            "N7": "GitHub Actions reads, claims a state lock, decides, writes back, waits for Raw release, finalizes, and prevents duplicate external mutation"
          },
          "state_signature": "d837f39dae9c875a",
          "truth_boundary": "N7 is externalized execution on GitHub Actions with checkpoint recovery and anti-reentry. It is still physical cloud CPU, not network-only computation."
        },
        "headers": {
          "cache-control": "max-age=300",
          "etag": "\"101c294f7dcdd5d90698ac00cb3373d371f2b152f1ff222c1692faa65a9f2ca6\"",
          "x-cache": "MISS",
          "x-served-by": "cache-dfw-kdfw8210089-DFW",
          "via": "1.1 varnish",
          "expires": "Fri, 17 Jul 2026 20:38:44 GMT"
        },
        "error": "",
        "index": 1,
        "sampled_at": "2026-07-17T20:33:44.097055+00:00"
      },
      {
        "ok": true,
        "status": 200,
        "elapsed_ms": 46.61,
        "generation": 258,
        "phase": "active",
        "state_signature": "d837f39dae9c875a",
        "body_sha16": "9826a30dac221358",
        "canonical_sha16": "5bb4feed1dedc993",
        "payload": {
          "stage": "N7-externalized-ghost-state-machine-with-lock",
          "created_at": "2026-07-17T20:33:42.092475+00:00",
          "generation": 258,
          "cycle_index": 250,
          "phase": "active",
          "event": "fast_release",
          "decision_reason": "previous branch shadow released quickly",
          "previous": {
            "generation": 257,
            "phase": "active",
            "state_signature": "ed8bdb91ba1e3128"
          },
          "release_memory": {
            "count": 256,
            "latest_seconds": 0.08,
            "mean_seconds": 332.276,
            "pending_current_release": true
          },
          "executor": {
            "layer": "github_actions",
            "workflow": "N6 External Ghost Runner",
            "run_id": "29611645401",
            "run_attempt": "1",
            "actor": "tong0202",
            "repository": "tong0202/qimingxing-test2-network-state-20260626-034447",
            "server_url": "https://github.com"
          },
          "network_role": {
            "N7": "GitHub Actions reads, claims a state lock, decides, writes back, waits for Raw release, finalizes, and prevents duplicate external mutation"
          },
          "state_signature": "d837f39dae9c875a",
          "truth_boundary": "N7 is externalized execution on GitHub Actions with checkpoint recovery and anti-reentry. It is still physical cloud CPU, not network-only computation."
        },
        "headers": {
          "cache-control": "max-age=300",
          "etag": "\"101c294f7dcdd5d90698ac00cb3373d371f2b152f1ff222c1692faa65a9f2ca6\"",
          "x-cache": "HIT",
          "x-served-by": "cache-dfw-kdfw8210094-DFW",
          "via": "1.1 varnish",
          "expires": "Fri, 17 Jul 2026 20:38:45 GMT"
        },
        "error": "",
        "index": 2,
        "sampled_at": "2026-07-17T20:33:45.144006+00:00"
      },
      {
        "ok": true,
        "status": 200,
        "elapsed_ms": 46.83,
        "generation": 258,
        "phase": "active",
        "state_signature": "d837f39dae9c875a",
        "body_sha16": "9826a30dac221358",
        "canonical_sha16": "5bb4feed1dedc993",
        "payload": {
          "stage": "N7-externalized-ghost-state-machine-with-lock",
          "created_at": "2026-07-17T20:33:42.092475+00:00",
          "generation": 258,
          "cycle_index": 250,
          "phase": "active",
          "event": "fast_release",
          "decision_reason": "previous branch shadow released quickly",
          "previous": {
            "generation": 257,
            "phase": "active",
            "state_signature": "ed8bdb91ba1e3128"
          },
          "release_memory": {
            "count": 256,
            "latest_seconds": 0.08,
            "mean_seconds": 332.276,
            "pending_current_release": true
          },
          "executor": {
            "layer": "github_actions",
            "workflow": "N6 External Ghost Runner",
            "run_id": "29611645401",
            "run_attempt": "1",
            "actor": "tong0202",
            "repository": "tong0202/qimingxing-test2-network-state-20260626-034447",
            "server_url": "https://github.com"
          },
          "network_role": {
            "N7": "GitHub Actions reads, claims a state lock, decides, writes back, waits for Raw release, finalizes, and prevents duplicate external mutation"
          },
          "state_signature": "d837f39dae9c875a",
          "truth_boundary": "N7 is externalized execution on GitHub Actions with checkpoint recovery and anti-reentry. It is still physical cloud CPU, not network-only computation."
        },
        "headers": {
          "cache-control": "max-age=300",
          "etag": "\"101c294f7dcdd5d90698ac00cb3373d371f2b152f1ff222c1692faa65a9f2ca6\"",
          "x-cache": "HIT",
          "x-served-by": "cache-dfw-kdfw8210108-DFW",
          "via": "1.1 varnish",
          "expires": "Fri, 17 Jul 2026 20:38:46 GMT"
        },
        "error": "",
        "index": 3,
        "sampled_at": "2026-07-17T20:33:46.191173+00:00"
      }
    ]
  },
  "branch_release": {
    "released": true,
    "release_after_seconds": 0.12,
    "branch_generations": [
      258
    ],
    "branch_signatures": [
      "d837f39dae9c875a"
    ],
    "branch_x_cache": [
      "MISS"
    ],
    "samples": [
      {
        "index": 1,
        "sampled_at": "2026-07-17T20:33:46.315586+00:00",
        "elapsed_since_write": 0.12,
        "branch": {
          "ok": true,
          "status": 200,
          "elapsed_ms": 124.24,
          "generation": 258,
          "phase": "active",
          "state_signature": "d837f39dae9c875a",
          "body_sha16": "9826a30dac221358",
          "canonical_sha16": "5bb4feed1dedc993",
          "payload": {
            "stage": "N7-externalized-ghost-state-machine-with-lock",
            "created_at": "2026-07-17T20:33:42.092475+00:00",
            "generation": 258,
            "cycle_index": 250,
            "phase": "active",
            "event": "fast_release",
            "decision_reason": "previous branch shadow released quickly",
            "previous": {
              "generation": 257,
              "phase": "active",
              "state_signature": "ed8bdb91ba1e3128"
            },
            "release_memory": {
              "count": 256,
              "latest_seconds": 0.08,
              "mean_seconds": 332.276,
              "pending_current_release": true
            },
            "executor": {
              "layer": "github_actions",
              "workflow": "N6 External Ghost Runner",
              "run_id": "29611645401",
              "run_attempt": "1",
              "actor": "tong0202",
              "repository": "tong0202/qimingxing-test2-network-state-20260626-034447",
              "server_url": "https://github.com"
            },
            "network_role": {
              "N7": "GitHub Actions reads, claims a state lock, decides, writes back, waits for Raw release, finalizes, and prevents duplicate external mutation"
            },
            "state_signature": "d837f39dae9c875a",
            "truth_boundary": "N7 is externalized execution on GitHub Actions with checkpoint recovery and anti-reentry. It is still physical cloud CPU, not network-only computation."
          },
          "headers": {
            "cache-control": "max-age=300",
            "etag": "\"101c294f7dcdd5d90698ac00cb3373d371f2b152f1ff222c1692faa65a9f2ca6\"",
            "x-cache": "MISS",
            "x-served-by": "cache-chi-kmdw8640098-CHI",
            "via": "1.1 varnish",
            "expires": "Fri, 17 Jul 2026 20:38:46 GMT"
          },
          "error": ""
        },
        "released": true
      }
    ]
  },
  "finalize": {
    "ok": true,
    "status": 200,
    "error": ""
  },
  "final_state": {
    "stage": "N7-externalized-ghost-state-machine-with-lock",
    "created_at": "2026-07-17T20:33:42.092475+00:00",
    "generation": 258,
    "cycle_index": 250,
    "phase": "active",
    "event": "fast_release",
    "decision_reason": "previous branch shadow released quickly",
    "previous": {
      "generation": 257,
      "phase": "active",
      "state_signature": "ed8bdb91ba1e3128"
    },
    "release_memory": {
      "count": 257,
      "latest_seconds": 0.12,
      "mean_seconds": 330.984,
      "pending_current_release": false
    },
    "executor": {
      "layer": "github_actions",
      "workflow": "N6 External Ghost Runner",
      "run_id": "29611645401",
      "run_attempt": "1",
      "actor": "tong0202",
      "repository": "tong0202/qimingxing-test2-network-state-20260626-034447",
      "server_url": "https://github.com"
    },
    "network_role": {
      "N7": "GitHub Actions reads, claims a state lock, decides, writes back, waits for Raw release, finalizes, and prevents duplicate external mutation"
    },
    "state_signature": "62b13cf363482cf9",
    "truth_boundary": "N7 is externalized execution on GitHub Actions with checkpoint recovery and anti-reentry. It is still physical cloud CPU, not network-only computation.",
    "self_release": {
      "release_after_seconds": 0.12,
      "observed_at": "2026-07-17T20:33:46.316347+00:00"
    }
  },
  "truth_boundary": "N7 proves external checkpointing and anti-reentry on GitHub Actions. It still uses GitHub cloud CPU and does not prove hardware-free network computation."
}
