{
  "stage": "N7-external-breakpoint-recovery-and-anti-reentry",
  "locked": false,
  "checkpoint": "completed",
  "owner": {
    "workflow": "N6 External Ghost Runner",
    "run_id": "29664687568",
    "run_attempt": "1",
    "actor": "tong0202",
    "repository": "tong0202/qimingxing-test2-network-state-20260626-034447",
    "server_url": "https://github.com"
  },
  "created_at": "2026-07-18T23:08:29.900486+00:00",
  "updated_at": "2026-07-18T23:08:35.844526+00:00",
  "expires_at": "2026-07-18T23:08:35.844533+00:00",
  "generation_before": 277,
  "target_generation": 278,
  "state_before": {
    "generation": 277,
    "phase": "active",
    "state_signature": "0998933f0dd48007",
    "content_sha": "f43e7ebf72c05386828aad4b7767ed732373385c"
  },
  "truth_boundary": "This is a state-level lock for external GitHub Actions execution. It is not hardware-free computation.",
  "events": [
    {
      "at": "2026-07-18T23:08:29.900525+00:00",
      "event": "lock_acquired"
    },
    {
      "at": "2026-07-18T23:08:31.607749+00:00",
      "event": "state_written",
      "target_generation": 278,
      "commit_hash": "ee463340ed60178ff6fcfeb0d2af0b5b1aca5a5b",
      "content_sha": "c86e80854a49cdae4f33d6fa5b42cb82bcef1888"
    },
    {
      "at": "2026-07-18T23:08:35.844511+00:00",
      "event": "completed",
      "target_generation": 278,
      "release_after_seconds": 0.1
    }
  ],
  "write": {
    "commit_hash": "ee463340ed60178ff6fcfeb0d2af0b5b1aca5a5b",
    "content_sha": "c86e80854a49cdae4f33d6fa5b42cb82bcef1888",
    "target_generation": 278
  },
  "completed_at": "2026-07-18T23:08:35.844531+00:00"
}
