{
  "stage": "N7-external-breakpoint-recovery-and-anti-reentry",
  "locked": false,
  "checkpoint": "completed",
  "owner": {
    "workflow": "N6 External Ghost Runner",
    "run_id": "28628700831",
    "run_attempt": "1",
    "actor": "tong0202",
    "repository": "tong0202/qimingxing-test2-network-state-20260626-034447",
    "server_url": "https://github.com"
  },
  "created_at": "2026-07-02T23:45:18.000283+00:00",
  "updated_at": "2026-07-02T23:45:24.279254+00:00",
  "expires_at": "2026-07-02T23:45:24.279258+00:00",
  "generation_before": 88,
  "target_generation": 89,
  "state_before": {
    "generation": 88,
    "phase": "active",
    "state_signature": "e9e5f246ebec5732",
    "content_sha": "cb3e3f48472baf81018bdc7c45fcf1e76bbd7188"
  },
  "truth_boundary": "This is a state-level lock for external GitHub Actions execution. It is not hardware-free computation.",
  "events": [
    {
      "at": "2026-07-02T23:45:18.000318+00:00",
      "event": "lock_acquired"
    },
    {
      "at": "2026-07-02T23:45:19.971669+00:00",
      "event": "state_written",
      "target_generation": 89,
      "commit_hash": "e1fcb636fe3d537a802256c0f31ce92eb0972e30",
      "content_sha": "a7243201d71d8fe1ab5d3cdd2e495742648629cf"
    },
    {
      "at": "2026-07-02T23:45:24.279240+00:00",
      "event": "completed",
      "target_generation": 89,
      "release_after_seconds": 0.15
    }
  ],
  "write": {
    "commit_hash": "e1fcb636fe3d537a802256c0f31ce92eb0972e30",
    "content_sha": "a7243201d71d8fe1ab5d3cdd2e495742648629cf",
    "target_generation": 89
  },
  "completed_at": "2026-07-02T23:45:24.279256+00:00"
}
