{
  "stage": "L12-hourly-self-maintenance-lock",
  "schema_version": "QMX-L12-LOCK-0.1",
  "locked": false,
  "checkpoint": "completed",
  "run_id": "nsl-l12-schedule-28455237628-attempt-1",
  "owner": {
    "mode": "external",
    "workflow": "L12 Hourly Self Maintenance",
    "run_id": "28455237628",
    "run_attempt": "1",
    "event_name": "schedule",
    "actor": "tong0202",
    "repository": "tong0202/qimingxing-test2-network-state-20260626-034447",
    "sha": "1cab117731e0446b34b6471f8f0b9c09b7568138",
    "local": false
  },
  "created_at": "2026-06-30T15:16:43.365401+00:00",
  "updated_at": "2026-06-30T15:16:53.423429+00:00",
  "expires_at": "2026-06-30T16:01:43.365411+00:00",
  "ttl_seconds": 2700,
  "previous_lock_recovered": false,
  "lock_hash": "bcac36871630f0fc",
  "truth_boundary": "This lock prevents overlapping L12 hourly self-maintenance windows. It is not autonomous network self-execution.",
  "released_at": "2026-06-30T15:16:53.423436+00:00",
  "release_ok": true
}
